bobotools/__init__.py
bobotools/com.py
bobotools/img_tools.py
bobotools/list_tools.py
bobotools/torch_tools.py
bobotools/txt_tools.py
bobotools-0.4.8.0.dist-info/LICENSE
bobotools-0.4.8.0.dist-info/METADATA
bobotools-0.4.8.0.dist-info/WHEEL
bobotools-0.4.8.0.dist-info/top_level.txt
bobotools-0.4.8.0.dist-info/RECORD
