Metadata-Version: 2.1
Name: bobotools
Version: 0.4.8.0
Summary: bobotools
Author: bobo0810
License: MIT
Classifier: Environment :: Console
Classifier: Natural Language :: English
Classifier: Development Status :: 4 - Beta
Classifier: Intended Audience :: Developers
Classifier: License :: OSI Approved :: MIT License
Classifier: Operating System :: OS Independent
Classifier: Programming Language :: Python :: 3
Requires-Python: >=3.6
License-File: LICENSE
Requires-Dist: pytest
Requires-Dist: tqdm
Requires-Dist: opencv-python-headless
Requires-Dist: numpy
Requires-Dist: ptflops
Requires-Dist: torch
Requires-Dist: torchvision
Requires-Dist: grad-cam
Requires-Dist: pillow
